latk/__init__.py
latk/latk_kmeans.py
latk/latk_main.py
latk/latk_rdp.py
latk/latk_tilt.py
latk/latk_zip.py
latk-2.9.2.dist-info/LICENSE.txt
latk-2.9.2.dist-info/METADATA
latk-2.9.2.dist-info/WHEEL
latk-2.9.2.dist-info/top_level.txt
latk-2.9.2.dist-info/RECORD
