Metadata-Version: 2.1
Name: latk
Version: 2.9.2
Summary: Lightning Artist Toolkit for volumetric animation
Home-page: https://fox-gieg.com
Author: Nick Fox-Gieg
Author-email: nick@fox-gieg.com
License: apache-2.0
Keywords: animation,blender,drawing
Classifier: Development Status :: 4 - Beta
Classifier: Intended Audience :: Developers
Classifier: Topic :: Multimedia :: Graphics :: 3D Modeling
Classifier: License :: OSI Approved :: Apache Software License
Classifier: Programming Language :: Python :: 3
License-File: LICENSE.txt
Requires-Dist: numpy
